{"day":1,"boards":[{"words":["hammer","bolt","jack","bud","brain","rose","under","war","thunder","king","horn","maker","shoe","storm","world","lord"],"pairs":[["brain","storm"],["king","maker"],["king","bolt"],["thunder","storm"],["thunder","bolt"],["shoe","maker"],["shoe","horn"],["rose","bud"],["under","world"],["jack","hammer"],["war","lord"]],"solution":[["jack","hammer"],["shoe","horn"],["king","maker"],["brain","storm"],["war","lord"],["under","world"],["rose","bud"],["thunder","bolt"]]},{"words":["hole","body","drop","shop","cart","view","down","dust","take","out","finder","surf","port","sweat","dug","snow"],"pairs":[["port","hole"],["dug","out"],["dust","cart"],["out","port"],["down","hole"],["body","surf"],["drop","out"],["sweat","shop"],["snow","drop"],["view","port"],["view","finder"],["take","out"],["take","down"]],"solution":[["snow","drop"],["take","down"],["dust","cart"],["view","finder"],["port","hole"],["sweat","shop"],["dug","out"],["body","surf"]]},{"words":["life","back","state","school","play","over","free","boarder","work","set","sail","site","hot","wheel","head","wild"],"pairs":[["free","wheel"],["set","back"],["sail","boarder"],["play","back"],["play","school"],["hot","head"],["over","state"],["over","set"],["over","play"],["over","head"],["over","work"],["school","work"],["wild","life"],["head","set"],["head","sail"],["head","work"],["work","site"]],"solution":[["over","state"],["set","back"],["hot","head"],["wild","life"],["play","school"],["work","site"],["free","wheel"],["sail","boarder"]]}]}